{
  "coins": [
    {
      "id": "bitcoin",
      "symbol": "btc",
      "name": "Bitcoin",
      "image": "https://coin-images.coingecko.com/coins/images/1/large/bitcoin.png?1696501400",
      "current_price": 69152,
      "market_cap": 1384228865733,
      "market_cap_rank": 1,
      "price_change_percentage_1h": 0.013524792767546102,
      "price_change_percentage_24h": 3.51055,
      "price_change_percentage_7d": 2.372999173951147,
      "price_change_percentage_30d": 1.589833011962728
    },
    {
      "id": "ethereum",
      "symbol": "eth",
      "name": "Ethereum",
      "image": "https://coin-images.coingecko.com/coins/images/279/large/ethereum.png?1696501628",
      "current_price": 2130.08,
      "market_cap": 257107927839,
      "market_cap_rank": 2,
      "price_change_percentage_1h": -0.007282394055385692,
      "price_change_percentage_24h": 4.23013,
      "price_change_percentage_7d": 4.061214266442695,
      "price_change_percentage_30d": 7.82120544363244
    },
    {
      "id": "tether",
      "symbol": "usdt",
      "name": "Tether",
      "image": "https://coin-images.coingecko.com/coins/images/325/large/Tether.png?1696501661",
      "current_price": 0.999691,
      "market_cap": 184098040966,
      "market_cap_rank": 3,
      "price_change_percentage_1h": -0.0005428075253255838,
      "price_change_percentage_24h": -0.01601,
      "price_change_percentage_7d": 0.05502778673924388,
      "price_change_percentage_30d": -0.02431580260677381
    },
    {
      "id": "ripple",
      "symbol": "xrp",
      "name": "XRP",
      "image": "https://coin-images.coingecko.com/coins/images/44/large/xrp-symbol-white-128.png?1696501442",
      "current_price": 1.34,
      "market_cap": 82230444167,
      "market_cap_rank": 4,
      "price_change_percentage_1h": 0.05794166990306922,
      "price_change_percentage_24h": 2.97101,
      "price_change_percentage_7d": -1.0113179039632958,
      "price_change_percentage_30d": -1.7873029045444984
    },
    {
      "id": "binancecoin",
      "symbol": "bnb",
      "name": "BNB",
      "image": "https://coin-images.coingecko.com/coins/images/825/large/bnb-icon2_2x.png?1696501970",
      "current_price": 602.8,
      "market_cap": 82083123436,
      "market_cap_rank": 5,
      "price_change_percentage_1h": 0.44064544202738354,
      "price_change_percentage_24h": 2.13311,
      "price_change_percentage_7d": -2.2239268582784013,
      "price_change_percentage_30d": -3.91405097923233
    },
    {
      "id": "usd-coin",
      "symbol": "usdc",
      "name": "USDC",
      "image": "https://coin-images.coingecko.com/coins/images/6319/large/USDC.png?1769615602",
      "current_price": 0.999776,
      "market_cap": 77507941149,
      "market_cap_rank": 6,
      "price_change_percentage_1h": -0.01908074920253703,
      "price_change_percentage_24h": -0.04901,
      "price_change_percentage_7d": -0.00413608554644664,
      "price_change_percentage_30d": -0.012909557155242087
    },
    {
      "id": "solana",
      "symbol": "sol",
      "name": "Solana",
      "image": "https://coin-images.coingecko.com/coins/images/4128/large/solana.png?1718769756",
      "current_price": 81.83,
      "market_cap": 46912968791,
      "market_cap_rank": 7,
      "price_change_percentage_1h": -0.1315240553152634,
      "price_change_percentage_24h": 2.15616,
      "price_change_percentage_7d": -2.2051384893854116,
      "price_change_percentage_30d": -2.983595405365271
    },
    {
      "id": "tron",
      "symbol": "trx",
      "name": "TRON",
      "image": "https://coin-images.coingecko.com/coins/images/1094/large/tron-logo.png?1696502193",
      "current_price": 0.317668,
      "market_cap": 30107811818,
      "market_cap_rank": 8,
      "price_change_percentage_1h": 0.05019532391519094,
      "price_change_percentage_24h": 0.02553,
      "price_change_percentage_7d": -1.1752284696203255,
      "price_change_percentage_30d": 11.869213526861927
    },
    {
      "id": "figure-heloc",
      "symbol": "figr_heloc",
      "name": "Figure Heloc",
      "image": "https://coin-images.coingecko.com/coins/images/68480/large/figure.png?1755863954",
      "current_price": 1.03,
      "market_cap": 16954981873,
      "market_cap_rank": 9,
      "price_change_percentage_1h": null,
      "price_change_percentage_24h": null,
      "price_change_percentage_7d": 1.0636942375040304,
      "price_change_percentage_30d": 0.5586328624469418
    },
    {
      "id": "dogecoin",
      "symbol": "doge",
      "name": "Dogecoin",
      "image": "https://coin-images.coingecko.com/coins/images/5/large/dogecoin.png?1696501409",
      "current_price": 0.092413,
      "market_cap": 14206632072,
      "market_cap_rank": 10,
      "price_change_percentage_1h": -0.21395464199480055,
      "price_change_percentage_24h": 2.01551,
      "price_change_percentage_7d": -0.7301278970341945,
      "price_change_percentage_30d": 1.8688295186897161
    },
    {
      "id": "usds",
      "symbol": "usds",
      "name": "USDS",
      "image": "https://coin-images.coingecko.com/coins/images/39926/large/usds.webp?1726666683",
      "current_price": 0.999606,
      "market_cap": 11826430937,
      "market_cap_rank": 11,
      "price_change_percentage_1h": -0.02965241691710474,
      "price_change_percentage_24h": -0.02386,
      "price_change_percentage_7d": -0.010633204519657057,
      "price_change_percentage_30d": -0.032484697210854084
    },
    {
      "id": "whitebit",
      "symbol": "wbt",
      "name": "WhiteBIT Coin",
      "image": "https://coin-images.coingecko.com/coins/images/27045/large/wbt_token.png?1696526096",
      "current_price": 52.33,
      "market_cap": 11168975308,
      "market_cap_rank": 12,
      "price_change_percentage_1h": 0.012597003947703187,
      "price_change_percentage_24h": 2.35097,
      "price_change_percentage_7d": 0.6418312414052391,
      "price_change_percentage_30d": -3.978087902457788
    },
    {
      "id": "cardano",
      "symbol": "ada",
      "name": "Cardano",
      "image": "https://coin-images.coingecko.com/coins/images/975/large/cardano.png?1696502090",
      "current_price": 0.2571,
      "market_cap": 9483068954,
      "market_cap_rank": 13,
      "price_change_percentage_1h": 0.009606071009380563,
      "price_change_percentage_24h": 5.41889,
      "price_change_percentage_7d": 4.435277853891346,
      "price_change_percentage_30d": -0.5741597346396283
    },
    {
      "id": "leo-token",
      "symbol": "leo",
      "name": "LEO Token",
      "image": "https://coin-images.coingecko.com/coins/images/8418/large/leo-token.png?1696508607",
      "current_price": 10.12,
      "market_cap": 9315614780,
      "market_cap_rank": 14,
      "price_change_percentage_1h": 0.011785449211845654,
      "price_change_percentage_24h": 0.46927,
      "price_change_percentage_7d": 4.401597513106925,
      "price_change_percentage_30d": 11.675677674077653
    },
    {
      "id": "hyperliquid",
      "symbol": "hype",
      "name": "Hyperliquid",
      "image": "https://coin-images.coingecko.com/coins/images/50882/large/hyperliquid.jpg?1729431300",
      "current_price": 36.96,
      "market_cap": 8815722891,
      "market_cap_rank": 15,
      "price_change_percentage_1h": 0.29940879675399973,
      "price_change_percentage_24h": 3.70834,
      "price_change_percentage_7d": -4.231327843141137,
      "price_change_percentage_30d": 20.925186736479816
    },
    {
      "id": "bitcoin-cash",
      "symbol": "bch",
      "name": "Bitcoin Cash",
      "image": "https://coin-images.coingecko.com/coins/images/780/large/bitcoin-cash-circle.png?1696501932",
      "current_price": 435.76,
      "market_cap": 8718814467,
      "market_cap_rank": 16,
      "price_change_percentage_1h": 0.26458499540798236,
      "price_change_percentage_24h": -0.11152,
      "price_change_percentage_7d": -4.342424225774214,
      "price_change_percentage_30d": -2.8852117058927083
    },
    {
      "id": "chainlink",
      "symbol": "link",
      "name": "Chainlink",
      "image": "https://coin-images.coingecko.com/coins/images/877/large/Chainlink_Logo_500.png?1760023405",
      "current_price": 8.95,
      "market_cap": 6506429203,
      "market_cap_rank": 17,
      "price_change_percentage_1h": 0.16536979028445403,
      "price_change_percentage_24h": 4.15421,
      "price_change_percentage_7d": 3.1941165620096883,
      "price_change_percentage_30d": 1.6829968834193205
    },
    {
      "id": "monero",
      "symbol": "xmr",
      "name": "Monero",
      "image": "https://coin-images.coingecko.com/coins/images/69/large/monero_logo.png?1696501460",
      "current_price": 329.89,
      "market_cap": 6088055194,
      "market_cap_rank": 18,
      "price_change_percentage_1h": -0.13843042689302615,
      "price_change_percentage_24h": 0.57994,
      "price_change_percentage_7d": -1.2938145307448543,
      "price_change_percentage_30d": -5.938693501480805
    },
    {
      "id": "ethena-usde",
      "symbol": "usde",
      "name": "Ethena USDe",
      "image": "https://coin-images.coingecko.com/coins/images/33613/large/usde.png?1733810059",
      "current_price": 0.99947,
      "market_cap": 5884726480,
      "market_cap_rank": 19,
      "price_change_percentage_1h": -0.004885943015705562,
      "price_change_percentage_24h": 0.00571,
      "price_change_percentage_7d": 0.07348826302250892,
      "price_change_percentage_30d": 0.036079973471592634
    },
    {
      "id": "stellar",
      "symbol": "xlm",
      "name": "Stellar",
      "image": "https://coin-images.coingecko.com/coins/images/100/large/fmpFRHHQ_400x400.jpg?1735231350",
      "current_price": 0.161197,
      "market_cap": 5335645329,
      "market_cap_rank": 20,
      "price_change_percentage_1h": -0.20180451908578093,
      "price_change_percentage_24h": 0.80134,
      "price_change_percentage_7d": -4.456187350716749,
      "price_change_percentage_30d": 5.951413409748291
    },
    {
      "id": "canton-network",
      "symbol": "cc",
      "name": "Canton",
      "image": "https://coin-images.coingecko.com/coins/images/70468/large/Canton-Ticker_%281%29.png?1762826299",
      "current_price": 0.139478,
      "market_cap": 5331699731,
      "market_cap_rank": 21,
      "price_change_percentage_1h": 0.4009739550932809,
      "price_change_percentage_24h": -0.40832,
      "price_change_percentage_7d": -9.331660719674877,
      "price_change_percentage_30d": -8.65046752118723
    },
    {
      "id": "memecore",
      "symbol": "m",
      "name": "MemeCore",
      "image": "https://coin-images.coingecko.com/coins/images/53247/large/square-bg-transparent.png?1752637478",
      "current_price": 2.77,
      "market_cap": 4858965628,
      "market_cap_rank": 22,
      "price_change_percentage_1h": 1.8292205431263988,
      "price_change_percentage_24h": 8.64432,
      "price_change_percentage_7d": 23.846941111545984,
      "price_change_percentage_30d": 84.15335235514104
    },
    {
      "id": "dai",
      "symbol": "dai",
      "name": "Dai",
      "image": "https://coin-images.coingecko.com/coins/images/9956/large/Badge_Dai.png?1696509996",
      "current_price": 1.001,
      "market_cap": 4441778590,
      "market_cap_rank": 23,
      "price_change_percentage_1h": 0.003018770825298845,
      "price_change_percentage_24h": 0.07691,
      "price_change_percentage_7d": 0.0997797062685298,
      "price_change_percentage_30d": 0.08049743854243305
    },
    {
      "id": "usd1-wlfi",
      "symbol": "usd1",
      "name": "USD1",
      "image": "https://coin-images.coingecko.com/coins/images/54977/large/USD1_1000x1000_transparent.png?1749297002",
      "current_price": 0.999778,
      "market_cap": 4412046094,
      "market_cap_rank": 24,
      "price_change_percentage_1h": -0.00016948829210385223,
      "price_change_percentage_24h": -0.02105,
      "price_change_percentage_7d": 0.05540869549967917,
      "price_change_percentage_30d": 0.0009074445473300346
    },
    {
      "id": "zcash",
      "symbol": "zec",
      "name": "Zcash",
      "image": "https://coin-images.coingecko.com/coins/images/486/large/circle-zcash-color.png?1696501740",
      "current_price": 254.26,
      "market_cap": 4252042808,
      "market_cap_rank": 25,
      "price_change_percentage_1h": 0.4057221267979098,
      "price_change_percentage_24h": 4.0026,
      "price_change_percentage_7d": 13.525846756024155,
      "price_change_percentage_30d": 21.814454180728035
    },
    {
      "id": "litecoin",
      "symbol": "ltc",
      "name": "Litecoin",
      "image": "https://coin-images.coingecko.com/coins/images/2/large/litecoin.png?1696501400",
      "current_price": 54.27,
      "market_cap": 4183425302,
      "market_cap_rank": 26,
      "price_change_percentage_1h": -0.07366071792263522,
      "price_change_percentage_24h": 2.49002,
      "price_change_percentage_7d": 0.37750638651176227,
      "price_change_percentage_30d": 0.7804912661994821
    },
    {
      "id": "avalanche-2",
      "symbol": "avax",
      "name": "Avalanche",
      "image": "https://coin-images.coingecko.com/coins/images/12559/large/Avalanche_Circle_RedWhite_Trans.png?1696512369",
      "current_price": 9.45,
      "market_cap": 4085468097,
      "market_cap_rank": 27,
      "price_change_percentage_1h": -0.1688423359895549,
      "price_change_percentage_24h": 6.70908,
      "price_change_percentage_7d": 7.063223800257133,
      "price_change_percentage_30d": 4.906854214146914
    },
    {
      "id": "paypal-usd",
      "symbol": "pyusd",
      "name": "PayPal USD",
      "image": "https://coin-images.coingecko.com/coins/images/31212/large/PYUSD_Token_Logo_2x.png?1765987788",
      "current_price": 0.999353,
      "market_cap": 3965243404,
      "market_cap_rank": 28,
      "price_change_percentage_1h": -0.036578615249457075,
      "price_change_percentage_24h": -0.05162,
      "price_change_percentage_7d": -0.0353680654304292,
      "price_change_percentage_30d": -0.06249959717435636
    },
    {
      "id": "hedera-hashgraph",
      "symbol": "hbar",
      "name": "Hedera",
      "image": "https://coin-images.coingecko.com/coins/images/3688/large/hbar.png?1696504364",
      "current_price": 0.088683,
      "market_cap": 3842961428,
      "market_cap_rank": 29,
      "price_change_percentage_1h": -0.5218249590054991,
      "price_change_percentage_24h": 2.06011,
      "price_change_percentage_7d": -1.2575225901522078,
      "price_change_percentage_30d": -8.581133346439245
    },
    {
      "id": "shiba-inu",
      "symbol": "shib",
      "name": "Shiba Inu",
      "image": "https://coin-images.coingecko.com/coins/images/11939/large/shiba.png?1696511800",
      "current_price": 0.000006,
      "market_cap": 3537698390,
      "market_cap_rank": 30,
      "price_change_percentage_1h": -0.20201907412456804,
      "price_change_percentage_24h": 2.46236,
      "price_change_percentage_7d": -0.22928314153040597,
      "price_change_percentage_30d": 10.863600720579942
    },
    {
      "id": "sui",
      "symbol": "sui",
      "name": "Sui",
      "image": "https://coin-images.coingecko.com/coins/images/26375/large/sui-ocean-square.png?1727791290",
      "current_price": 0.885178,
      "market_cap": 3505469801,
      "market_cap_rank": 31,
      "price_change_percentage_1h": -0.5661870742173195,
      "price_change_percentage_24h": 3.39806,
      "price_change_percentage_7d": 1.6011355119718895,
      "price_change_percentage_30d": -2.0924681021073246
    },
    {
      "id": "rain",
      "symbol": "rain",
      "name": "Rain",
      "image": "https://coin-images.coingecko.com/coins/images/69134/large/Rain_logo_1_.png?1762952191",
      "current_price": 0.00658146,
      "market_cap": 3146610322,
      "market_cap_rank": 32,
      "price_change_percentage_1h": 0.014313934770031551,
      "price_change_percentage_24h": -8.75768,
      "price_change_percentage_7d": -19.209208876180195,
      "price_change_percentage_30d": -27.460909439261084
    },
    {
      "id": "the-open-network",
      "symbol": "ton",
      "name": "Toncoin",
      "image": "https://coin-images.coingecko.com/coins/images/17980/large/photo_2024-09-10_17.09.00.jpeg?1725963446",
      "current_price": 1.25,
      "market_cap": 3100737034,
      "market_cap_rank": 33,
      "price_change_percentage_1h": -0.04972946324556253,
      "price_change_percentage_24h": 0.98783,
      "price_change_percentage_7d": 1.0894610000251095,
      "price_change_percentage_30d": -6.589091439113181
    },
    {
      "id": "bittensor",
      "symbol": "tao",
      "name": "Bittensor",
      "image": "https://coin-images.coingecko.com/coins/images/28452/large/ARUsPeNQ_400x400.jpeg?1696527447",
      "current_price": 317.57,
      "market_cap": 3065815049,
      "market_cap_rank": 34,
      "price_change_percentage_1h": 0.10190007088392229,
      "price_change_percentage_24h": 5.23693,
      "price_change_percentage_7d": -2.9406758672472906,
      "price_change_percentage_30d": 80.54392731282569
    },
    {
      "id": "world-liberty-financial",
      "symbol": "wlfi",
      "name": "World Liberty Financial",
      "image": "https://coin-images.coingecko.com/coins/images/50767/large/wlfi.png?1756438915",
      "current_price": 0.098643,
      "market_cap": 3033822187,
      "market_cap_rank": 35,
      "price_change_percentage_1h": -0.1644745729714469,
      "price_change_percentage_24h": 1.20829,
      "price_change_percentage_7d": -0.39825201148540523,
      "price_change_percentage_30d": -0.6202177936508566
    },
    {
      "id": "crypto-com-chain",
      "symbol": "cro",
      "name": "Cronos",
      "image": "https://coin-images.coingecko.com/coins/images/7310/large/cro_token_logo.png?1696507599",
      "current_price": 0.069861,
      "market_cap": 2958102759,
      "market_cap_rank": 36,
      "price_change_percentage_1h": -0.10356007952070267,
      "price_change_percentage_24h": 1.08382,
      "price_change_percentage_7d": -2.045310836924718,
      "price_change_percentage_30d": -7.763611059178513
    },
    {
      "id": "hashnote-usyc",
      "symbol": "usyc",
      "name": "Circle USYC",
      "image": "https://coin-images.coingecko.com/coins/images/51054/large/Hashnote_SDYC_200x200.png?1730370965",
      "current_price": 1.12,
      "market_cap": 2702544220,
      "market_cap_rank": 37,
      "price_change_percentage_1h": null,
      "price_change_percentage_24h": null,
      "price_change_percentage_7d": 0.16067642280987574,
      "price_change_percentage_30d": 0.21376808082486876
    },
    {
      "id": "tether-gold",
      "symbol": "xaut",
      "name": "Tether Gold",
      "image": "https://coin-images.coingecko.com/coins/images/10481/large/logo.png?1774627372",
      "current_price": 4625.07,
      "market_cap": 2588572557,
      "market_cap_rank": 38,
      "price_change_percentage_1h": -0.101960842737744,
      "price_change_percentage_24h": -0.20867,
      "price_change_percentage_7d": 2.4104763416051305,
      "price_change_percentage_30d": -10.083778120751502
    },
    {
      "id": "pax-gold",
      "symbol": "paxg",
      "name": "PAX Gold",
      "image": "https://coin-images.coingecko.com/coins/images/9519/large/paxgold.png?1696509604",
      "current_price": 4641.94,
      "market_cap": 2387460385,
      "market_cap_rank": 39,
      "price_change_percentage_1h": -0.104066301895086,
      "price_change_percentage_24h": -0.14592,
      "price_change_percentage_7d": 2.554395059365365,
      "price_change_percentage_30d": -10.410724710791557
    },
    {
      "id": "blackrock-usd-institutional-digital-liquidity-fund",
      "symbol": "buidl",
      "name": "BlackRock USD Institutional Digital Liquidity Fund",
      "image": "https://coin-images.coingecko.com/coins/images/36291/large/blackrock.png?1711013223",
      "current_price": 1,
      "market_cap": 2298435926,
      "market_cap_rank": 40,
      "price_change_percentage_1h": 0,
      "price_change_percentage_24h": 0,
      "price_change_percentage_7d": 0,
      "price_change_percentage_30d": 0
    },
    {
      "id": "mantle",
      "symbol": "mnt",
      "name": "Mantle",
      "image": "https://coin-images.coingecko.com/coins/images/30980/large/MNT_Token_Logo.png?1765516974",
      "current_price": 0.671457,
      "market_cap": 2201462704,
      "market_cap_rank": 41,
      "price_change_percentage_1h": -0.323820579549417,
      "price_change_percentage_24h": 2.13454,
      "price_change_percentage_7d": -1.654786819133199,
      "price_change_percentage_30d": -1.53504706204135
    },
    {
      "id": "polkadot",
      "symbol": "dot",
      "name": "Polkadot",
      "image": "https://coin-images.coingecko.com/coins/images/12171/large/polkadot.jpg?1766533446",
      "current_price": 1.26,
      "market_cap": 2115201327,
      "market_cap_rank": 42,
      "price_change_percentage_1h": 0.16654697829677734,
      "price_change_percentage_24h": 2.16498,
      "price_change_percentage_7d": -0.9648973993654284,
      "price_change_percentage_30d": -16.123398922456165
    },
    {
      "id": "uniswap",
      "symbol": "uni",
      "name": "Uniswap",
      "image": "https://coin-images.coingecko.com/coins/images/12504/large/uniswap-logo.png?1720676669",
      "current_price": 3.16,
      "market_cap": 2005571275,
      "market_cap_rank": 43,
      "price_change_percentage_1h": 0.09472765047828025,
      "price_change_percentage_24h": 2.76449,
      "price_change_percentage_7d": -8.959080469422966,
      "price_change_percentage_30d": -17.232763637093292
    },
    {
      "id": "global-dollar",
      "symbol": "usdg",
      "name": "Global Dollar",
      "image": "https://coin-images.coingecko.com/coins/images/51281/large/GDN_USDG_Token_200x200.png?1730484111",
      "current_price": 0.999715,
      "market_cap": 1862696118,
      "market_cap_rank": 44,
      "price_change_percentage_1h": -0.02107488570020527,
      "price_change_percentage_24h": -0.01018,
      "price_change_percentage_7d": -0.021532342905166722,
      "price_change_percentage_30d": -0.028192265250804694
    },
    {
      "id": "falcon-finance",
      "symbol": "usdf",
      "name": "Falcon USD",
      "image": "https://coin-images.coingecko.com/coins/images/54558/large/ff_200_X_200.png?1740741076",
      "current_price": 0.997534,
      "market_cap": 1741809169,
      "market_cap_rank": 45,
      "price_change_percentage_1h": 0.004243850511751027,
      "price_change_percentage_24h": -0.03479,
      "price_change_percentage_7d": -0.051458650404124,
      "price_change_percentage_30d": -0.006578842035840249
    },
    {
      "id": "okb",
      "symbol": "okb",
      "name": "OKB",
      "image": "https://coin-images.coingecko.com/coins/images/4463/large/WeChat_Image_20220118095654.png?1696505053",
      "current_price": 82.9,
      "market_cap": 1740896085,
      "market_cap_rank": 46,
      "price_change_percentage_1h": -0.1880438779417672,
      "price_change_percentage_24h": 0.26151,
      "price_change_percentage_7d": -2.501269361479887,
      "price_change_percentage_30d": -14.2518997668629
    },
    {
      "id": "pi-network",
      "symbol": "pi",
      "name": "Pi Network",
      "image": "https://coin-images.coingecko.com/coins/images/54342/large/pi_network.jpg?1739347576",
      "current_price": 0.171398,
      "market_cap": 1735118009,
      "market_cap_rank": 47,
      "price_change_percentage_1h": -0.18728823515241588,
      "price_change_percentage_24h": 0.36994,
      "price_change_percentage_7d": -4.035950210220117,
      "price_change_percentage_30d": -24.890177369181878
    },
    {
      "id": "sky",
      "symbol": "sky",
      "name": "Sky",
      "image": "https://coin-images.coingecko.com/coins/images/39925/large/sky.jpg?1724827980",
      "current_price": 0.074883,
      "market_cap": 1731736305,
      "market_cap_rank": 48,
      "price_change_percentage_1h": -0.16365760756244455,
      "price_change_percentage_24h": 1.03865,
      "price_change_percentage_7d": 2.073934658128601,
      "price_change_percentage_30d": 7.1291433452530235
    },
    {
      "id": "near",
      "symbol": "near",
      "name": "NEAR Protocol",
      "image": "https://coin-images.coingecko.com/coins/images/10365/large/near.jpg?1696510367",
      "current_price": 1.27,
      "market_cap": 1643700588,
      "market_cap_rank": 49,
      "price_change_percentage_1h": -0.3354603861596427,
      "price_change_percentage_24h": 1.85855,
      "price_change_percentage_7d": 5.948684179308907,
      "price_change_percentage_30d": 3.309692321173457
    },
    {
      "id": "aster-2",
      "symbol": "aster",
      "name": "Aster",
      "image": "https://coin-images.coingecko.com/coins/images/69040/large/_ASTER.png?1757326782",
      "current_price": 0.667707,
      "market_cap": 1641132642,
      "market_cap_rank": 50,
      "price_change_percentage_1h": 0.26142547055188464,
      "price_change_percentage_24h": 0.18715,
      "price_change_percentage_7d": 0.12148380979994117,
      "price_change_percentage_30d": -4.388933340894939
    },
    {
      "id": "htx-dao",
      "symbol": "htx",
      "name": "HTX DAO",
      "image": "https://coin-images.coingecko.com/coins/images/35491/large/Frame_1321318576.png?1708908626",
      "current_price": 0.00000174,
      "market_cap": 1593529637,
      "market_cap_rank": 51,
      "price_change_percentage_1h": 0.05408703383718149,
      "price_change_percentage_24h": 0.83342,
      "price_change_percentage_7d": 0.32188567304170757,
      "price_change_percentage_30d": 8.793882220060937
    },
    {
      "id": "usdd",
      "symbol": "usdd",
      "name": "USDD",
      "image": "https://coin-images.coingecko.com/coins/images/25380/large/UUSD.jpg?1696524513",
      "current_price": 1,
      "market_cap": 1540940774,
      "market_cap_rank": 52,
      "price_change_percentage_1h": 0.06079335541392728,
      "price_change_percentage_24h": 0.12801,
      "price_change_percentage_7d": 0.21641572480422844,
      "price_change_percentage_30d": 0.03447146698039458
    },
    {
      "id": "pepe",
      "symbol": "pepe",
      "name": "Pepe",
      "image": "https://coin-images.coingecko.com/coins/images/29850/large/pepe-token.jpeg?1696528776",
      "current_price": 0.00000351,
      "market_cap": 1478004676,
      "market_cap_rank": 53,
      "price_change_percentage_1h": -0.7747677737054746,
      "price_change_percentage_24h": 4.70853,
      "price_change_percentage_7d": 4.651114610555607,
      "price_change_percentage_30d": 4.032733073341716
    },
    {
      "id": "aave",
      "symbol": "aave",
      "name": "Aave",
      "image": "https://coin-images.coingecko.com/coins/images/12645/large/aave-token-round.png?1720472354",
      "current_price": 95.63,
      "market_cap": 1452307164,
      "market_cap_rank": 54,
      "price_change_percentage_1h": -0.025539080840990942,
      "price_change_percentage_24h": 2.52022,
      "price_change_percentage_7d": -2.127562275668556,
      "price_change_percentage_30d": -13.269459030345343
    },
    {
      "id": "ripple-usd",
      "symbol": "rlusd",
      "name": "Ripple USD",
      "image": "https://coin-images.coingecko.com/coins/images/39651/large/RLUSD_200x200_%281%29.png?1727376633",
      "current_price": 1,
      "market_cap": 1371039311,
      "market_cap_rank": 55,
      "price_change_percentage_1h": 0.030269662379200597,
      "price_change_percentage_24h": 0.0301,
      "price_change_percentage_7d": 0.014006855596804242,
      "price_change_percentage_30d": 0.022613842586108802
    },
    {
      "id": "ethereum-classic",
      "symbol": "etc",
      "name": "Ethereum Classic",
      "image": "https://coin-images.coingecko.com/coins/images/453/large/ethereum-classic-logo.png?1696501717",
      "current_price": 8.68,
      "market_cap": 1354757986,
      "market_cap_rank": 56,
      "price_change_percentage_1h": -0.36659693403782995,
      "price_change_percentage_24h": 2.7573,
      "price_change_percentage_7d": 5.65328665656725,
      "price_change_percentage_30d": 5.732783938343874
    },
    {
      "id": "bfusd",
      "symbol": "bfusd",
      "name": "BFUSD",
      "image": "https://coin-images.coingecko.com/coins/images/68227/large/bfusd.png?1755132827",
      "current_price": 0.9994,
      "market_cap": 1319208501,
      "market_cap_rank": 57,
      "price_change_percentage_1h": -0.009995366029991463,
      "price_change_percentage_24h": 0.00027,
      "price_change_percentage_7d": 0.08008316412643308,
      "price_change_percentage_30d": 0.010218382371276138
    },
    {
      "id": "bitget-token",
      "symbol": "bgb",
      "name": "Bitget Token",
      "image": "https://coin-images.coingecko.com/coins/images/11610/large/Bitget_logo.png?1736925727",
      "current_price": 1.87,
      "market_cap": 1309944297,
      "market_cap_rank": 58,
      "price_change_percentage_1h": 0.05400740895624668,
      "price_change_percentage_24h": -1.86668,
      "price_change_percentage_7d": -3.425843661532883,
      "price_change_percentage_30d": -13.559713478486973
    },
    {
      "id": "ondo-us-dollar-yield",
      "symbol": "usdy",
      "name": "Ondo US Dollar Yield",
      "image": "https://coin-images.coingecko.com/coins/images/31700/large/usdy_%281%29.png?1696530524",
      "current_price": 1.11,
      "market_cap": 1302390319,
      "market_cap_rank": 59,
      "price_change_percentage_1h": -0.0005977368576744908,
      "price_change_percentage_24h": -0.97036,
      "price_change_percentage_7d": -1.19776432263801,
      "price_change_percentage_30d": -0.8491368093725629
    },
    {
      "id": "ondo-finance",
      "symbol": "ondo",
      "name": "Ondo",
      "image": "https://coin-images.coingecko.com/coins/images/26580/large/ONDO.png?1696525656",
      "current_price": 0.262848,
      "market_cap": 1282530469,
      "market_cap_rank": 60,
      "price_change_percentage_1h": -1.3504809947482586,
      "price_change_percentage_24h": 4.54397,
      "price_change_percentage_7d": -2.6016271310631294,
      "price_change_percentage_30d": 3.8635528070032135
    },
    {
      "id": "internet-computer",
      "symbol": "icp",
      "name": "Internet Computer",
      "image": "https://coin-images.coingecko.com/coins/images/14495/large/Internet_Computer_logo.png?1696514180",
      "current_price": 2.32,
      "market_cap": 1276281306,
      "market_cap_rank": 61,
      "price_change_percentage_1h": -0.09186941665180853,
      "price_change_percentage_24h": 2.26484,
      "price_change_percentage_7d": 3.0113162346417295,
      "price_change_percentage_30d": -5.8566159466731635
    },
    {
      "id": "janus-henderson-anemoy-treasury-fund",
      "symbol": "jtrsy",
      "name": "Janus Henderson Anemoy Treasury Fund",
      "image": "https://coin-images.coingecko.com/coins/images/70445/large/JTRSY.png?1762078582",
      "current_price": 1.099,
      "market_cap": 1241371700,
      "market_cap_rank": 62,
      "price_change_percentage_1h": 0,
      "price_change_percentage_24h": 0,
      "price_change_percentage_7d": 0.094140011872221,
      "price_change_percentage_30d": 0.27508660302705895
    },
    {
      "id": "gatechain-token",
      "symbol": "gt",
      "name": "Gate",
      "image": "https://coin-images.coingecko.com/coins/images/8183/large/200X200.png?1735246724",
      "current_price": 6.51,
      "market_cap": 1133103428,
      "market_cap_rank": 63,
      "price_change_percentage_1h": 0.1180355782322721,
      "price_change_percentage_24h": 0.20292,
      "price_change_percentage_7d": -1.1503888039810601,
      "price_change_percentage_30d": -6.637755616583865
    },
    {
      "id": "quant-network",
      "symbol": "qnt",
      "name": "Quant",
      "image": "https://coin-images.coingecko.com/coins/images/3370/large/5ZOu7brX_400x400.jpg?1696504070",
      "current_price": 76.06,
      "market_cap": 1107772185,
      "market_cap_rank": 64,
      "price_change_percentage_1h": -0.15701426970616708,
      "price_change_percentage_24h": 2.0698,
      "price_change_percentage_7d": 8.386963399521411,
      "price_change_percentage_30d": 14.541588636228028
    },
    {
      "id": "kucoin-shares",
      "symbol": "kcs",
      "name": "KuCoin",
      "image": "https://coin-images.coingecko.com/coins/images/1047/large/sa9z79.png?1696502152",
      "current_price": 8.17,
      "market_cap": 1100558643,
      "market_cap_rank": 65,
      "price_change_percentage_1h": -0.24817613772451577,
      "price_change_percentage_24h": 1.54091,
      "price_change_percentage_7d": 0.6277136191092155,
      "price_change_percentage_30d": 4.530920281642216
    },
    {
      "id": "algorand",
      "symbol": "algo",
      "name": "Algorand",
      "image": "https://coin-images.coingecko.com/coins/images/4380/large/download.png?1696504978",
      "current_price": 0.123553,
      "market_cap": 1093816911,
      "market_cap_rank": 66,
      "price_change_percentage_1h": -0.58196045334937,
      "price_change_percentage_24h": 4.93429,
      "price_change_percentage_7d": 49.72539755806181,
      "price_change_percentage_30d": 46.03204546288279
    },
    {
      "id": "render-token",
      "symbol": "render",
      "name": "Render",
      "image": "https://coin-images.coingecko.com/coins/images/11636/large/rndr.png?1696511529",
      "current_price": 1.96,
      "market_cap": 1018990883,
      "market_cap_rank": 67,
      "price_change_percentage_1h": -1.3840035325594824,
      "price_change_percentage_24h": 4.22083,
      "price_change_percentage_7d": 13.333061152000155,
      "price_change_percentage_30d": 45.72620815912213
    },
    {
      "id": "pump-fun",
      "symbol": "pump",
      "name": "Pump.fun",
      "image": "https://coin-images.coingecko.com/coins/images/67164/large/pump.jpg?1751949376",
      "current_price": 0.00171217,
      "market_cap": 1010207482,
      "market_cap_rank": 68,
      "price_change_percentage_1h": -0.10750014030569904,
      "price_change_percentage_24h": 4.09096,
      "price_change_percentage_7d": -0.5098188017613159,
      "price_change_percentage_30d": -9.013124844336318
    },
    {
      "id": "superstate-short-duration-us-government-securities-fund-ustb",
      "symbol": "ustb",
      "name": "Superstate Short Duration U.S. Government Securities Fund (USTB)",
      "image": "https://coin-images.coingecko.com/coins/images/35012/large/ustb.jpeg?1707102680",
      "current_price": 11.04,
      "market_cap": 1005813312,
      "market_cap_rank": 69,
      "price_change_percentage_1h": 0,
      "price_change_percentage_24h": 0,
      "price_change_percentage_7d": 0.05723046255882083,
      "price_change_percentage_30d": 0.255549979193086
    },
    {
      "id": "polygon-ecosystem-token",
      "symbol": "pol",
      "name": "POL (ex-MATIC)",
      "image": "https://coin-images.coingecko.com/coins/images/32440/large/pol.png?1759114181",
      "current_price": 0.093087,
      "market_cap": 988878483,
      "market_cap_rank": 70,
      "price_change_percentage_1h": -0.1334253173540083,
      "price_change_percentage_24h": 2.33217,
      "price_change_percentage_7d": -0.19529543291078572,
      "price_change_percentage_30d": -5.791770066084314
    },
    {
      "id": "eutbl",
      "symbol": "eutbl",
      "name": "Spiko EU T-Bills Money Market Fund",
      "image": "https://coin-images.coingecko.com/coins/images/39657/large/EUTBL.png?1723517425",
      "current_price": 1.21,
      "market_cap": 922134883,
      "market_cap_rank": 71,
      "price_change_percentage_1h": -0.005416999466371301,
      "price_change_percentage_24h": 0.04368,
      "price_change_percentage_7d": 0.09200797760835161,
      "price_change_percentage_30d": -0.7008176916752088
    },
    {
      "id": "usdtb",
      "symbol": "usdtb",
      "name": "USDtb",
      "image": "https://coin-images.coingecko.com/coins/images/52804/large/76357aa8-4ef7-446c-bad3-a3f944eeec7a.jpeg?1758277468",
      "current_price": 0.999937,
      "market_cap": 864070498,
      "market_cap_rank": 72,
      "price_change_percentage_1h": 0.24677695031050714,
      "price_change_percentage_24h": 0.03762,
      "price_change_percentage_7d": 0.0399960175015918,
      "price_change_percentage_30d": 0.04145882011260393
    },
    {
      "id": "cosmos",
      "symbol": "atom",
      "name": "Cosmos Hub",
      "image": "https://coin-images.coingecko.com/coins/images/1481/large/cosmos_hub.png?1696502525",
      "current_price": 1.71,
      "market_cap": 857966158,
      "market_cap_rank": 73,
      "price_change_percentage_1h": -0.07697993199279103,
      "price_change_percentage_24h": 0.09928,
      "price_change_percentage_7d": 2.08655793631347,
      "price_change_percentage_30d": -6.500340721323994
    },
    {
      "id": "kaspa",
      "symbol": "kas",
      "name": "Kaspa",
      "image": "https://coin-images.coingecko.com/coins/images/25751/large/kaspa-icon-exchanges.png?1696524837",
      "current_price": 0.03135927,
      "market_cap": 855959427,
      "market_cap_rank": 74,
      "price_change_percentage_1h": 0.14876825491091936,
      "price_change_percentage_24h": 1.94837,
      "price_change_percentage_7d": -4.941770956436097,
      "price_change_percentage_30d": 4.946174815580929
    },
    {
      "id": "nexo",
      "symbol": "nexo",
      "name": "NEXO",
      "image": "https://coin-images.coingecko.com/coins/images/3695/large/CG-nexo-token-200x200_2x.png?1730414360",
      "current_price": 0.848662,
      "market_cap": 848552266,
      "market_cap_rank": 75,
      "price_change_percentage_1h": -0.11717399419165261,
      "price_change_percentage_24h": -0.41255,
      "price_change_percentage_7d": -4.960190577957849,
      "price_change_percentage_30d": -1.199834039443905
    },
    {
      "id": "morpho",
      "symbol": "morpho",
      "name": "Morpho",
      "image": "https://coin-images.coingecko.com/coins/images/29837/large/Morpho-token-icon.png?1726771230",
      "current_price": 1.51,
      "market_cap": 833539170,
      "market_cap_rank": 76,
      "price_change_percentage_1h": -0.40312675035440076,
      "price_change_percentage_24h": 3.26387,
      "price_change_percentage_7d": -1.8887657247070435,
      "price_change_percentage_30d": -16.59338147639617
    },
    {
      "id": "worldcoin-wld",
      "symbol": "wld",
      "name": "Worldcoin",
      "image": "https://coin-images.coingecko.com/coins/images/31069/large/worldcoin.jpeg?1696529903",
      "current_price": 0.247501,
      "market_cap": 805131847,
      "market_cap_rank": 77,
      "price_change_percentage_1h": -1.390643588873999,
      "price_change_percentage_24h": -2.13255,
      "price_change_percentage_7d": -12.045216483134338,
      "price_change_percentage_30d": -36.39854018983182
    },
    {
      "id": "ethena",
      "symbol": "ena",
      "name": "Ethena",
      "image": "https://coin-images.coingecko.com/coins/images/36530/large/ethena.png?1711701436",
      "current_price": 0.080822,
      "market_cap": 709290519,
      "market_cap_rank": 78,
      "price_change_percentage_1h": -0.3355669998125036,
      "price_change_percentage_24h": 3.34992,
      "price_change_percentage_7d": -11.505048622915785,
      "price_change_percentage_30d": -21.017379017283456
    },
    {
      "id": "midnight-3",
      "symbol": "night",
      "name": "Midnight",
      "image": "https://coin-images.coingecko.com/coins/images/71015/large/midnight.png?1765193080",
      "current_price": 0.04201748,
      "market_cap": 698805992,
      "market_cap_rank": 79,
      "price_change_percentage_1h": -0.06864506568908264,
      "price_change_percentage_24h": -1.12291,
      "price_change_percentage_7d": -13.787526035603351,
      "price_change_percentage_30d": -27.69765670723765
    },
    {
      "id": "aptos",
      "symbol": "apt",
      "name": "Aptos",
      "image": "https://coin-images.coingecko.com/coins/images/26455/large/Aptos-Network-Symbol-Black-RGB-1x.png?1761789140",
      "current_price": 0.851785,
      "market_cap": 677557010,
      "market_cap_rank": 80,
      "price_change_percentage_1h": -0.1297627154718388,
      "price_change_percentage_24h": 1.93555,
      "price_change_percentage_7d": -8.745914883424565,
      "price_change_percentage_30d": -11.187280991421913
    },
    {
      "id": "official-trump",
      "symbol": "trump",
      "name": "Official Trump",
      "image": "https://coin-images.coingecko.com/coins/images/53746/large/trump.png?1737171561",
      "current_price": 2.9,
      "market_cap": 675209788,
      "market_cap_rank": 81,
      "price_change_percentage_1h": -0.7448045668715152,
      "price_change_percentage_24h": 1.59484,
      "price_change_percentage_7d": -1.9591355898643705,
      "price_change_percentage_30d": -6.869711032840104
    },
    {
      "id": "ousg",
      "symbol": "ousg",
      "name": "OUSG",
      "image": "https://coin-images.coingecko.com/coins/images/29023/large/OUSG.png?1696527993",
      "current_price": 114.79,
      "market_cap": 670206413,
      "market_cap_rank": 82,
      "price_change_percentage_1h": 0,
      "price_change_percentage_24h": 0,
      "price_change_percentage_7d": 0.05580691645427066,
      "price_change_percentage_30d": 0.2501451418223998
    },
    {
      "id": "filecoin",
      "symbol": "fil",
      "name": "Filecoin",
      "image": "https://coin-images.coingecko.com/coins/images/12817/large/filecoin.png?1696512609",
      "current_price": 0.85225,
      "market_cap": 655839966,
      "market_cap_rank": 83,
      "price_change_percentage_1h": -0.09925713234737799,
      "price_change_percentage_24h": 3.57783,
      "price_change_percentage_7d": 1.6799824830316976,
      "price_change_percentage_30d": -12.416918808395854
    },
    {
      "id": "flare-networks",
      "symbol": "flr",
      "name": "Flare",
      "image": "https://coin-images.coingecko.com/coins/images/28624/large/FLR-icon200x200.png?1696527609",
      "current_price": 0.00749295,
      "market_cap": 641495368,
      "market_cap_rank": 84,
      "price_change_percentage_1h": -0.10267998935956475,
      "price_change_percentage_24h": -0.11543,
      "price_change_percentage_7d": -3.941718936815227,
      "price_change_percentage_30d": -15.91264047417688
    },
    {
      "id": "vechain",
      "symbol": "vet",
      "name": "VeChain",
      "image": "https://coin-images.coingecko.com/coins/images/1167/large/VET.png?1742383283",
      "current_price": 0.00745928,
      "market_cap": 641358429,
      "market_cap_rank": 85,
      "price_change_percentage_1h": -0.23875397740626428,
      "price_change_percentage_24h": -0.67531,
      "price_change_percentage_7d": 10.880743442643228,
      "price_change_percentage_30d": 5.326610746670279
    },
    {
      "id": "hash-2",
      "symbol": "hash",
      "name": "Provenance Blockchain",
      "image": "https://coin-images.coingecko.com/coins/images/66154/large/Hastra_Icon.png?1748497203",
      "current_price": 0.01132127,
      "market_cap": 639699772,
      "market_cap_rank": 86,
      "price_change_percentage_1h": -0.06072398885715206,
      "price_change_percentage_24h": -0.81276,
      "price_change_percentage_7d": 6.9660843126019705,
      "price_change_percentage_30d": -15.856371912608166
    },
    {
      "id": "ylds",
      "symbol": "ylds",
      "name": "YLDS",
      "image": "https://coin-images.coingecko.com/coins/images/66486/large/YLDS.png?1772560579",
      "current_price": 0.999938,
      "market_cap": 621030715,
      "market_cap_rank": 87,
      "price_change_percentage_1h": 0.006212095746477493,
      "price_change_percentage_24h": -0.00527,
      "price_change_percentage_7d": 0.007833332077491905,
      "price_change_percentage_30d": -0.006132548285101681
    },
    {
      "id": "beldex",
      "symbol": "bdx",
      "name": "Beldex",
      "image": "https://coin-images.coingecko.com/coins/images/5111/large/Beldex.png?1696505631",
      "current_price": 0.080085,
      "market_cap": 619024032,
      "market_cap_rank": 88,
      "price_change_percentage_1h": 0.16189580615087185,
      "price_change_percentage_24h": 0.12789,
      "price_change_percentage_7d": 0.09768916446436825,
      "price_change_percentage_30d": 0.34214101115718654
    },
    {
      "id": "xdce-crowd-sale",
      "symbol": "xdc",
      "name": "XDC Network",
      "image": "https://coin-images.coingecko.com/coins/images/2912/large/xdc-icon.png?1696503661",
      "current_price": 0.03080661,
      "market_cap": 613532597,
      "market_cap_rank": 89,
      "price_change_percentage_1h": 0.8891853180783055,
      "price_change_percentage_24h": -0.17388,
      "price_change_percentage_7d": 0.3844989042736491,
      "price_change_percentage_30d": -6.541511963986192
    },
    {
      "id": "jupiter-exchange-solana",
      "symbol": "jup",
      "name": "Jupiter",
      "image": "https://coin-images.coingecko.com/coins/images/34188/large/jup.png?1704266489",
      "current_price": 0.164912,
      "market_cap": 586121171,
      "market_cap_rank": 90,
      "price_change_percentage_1h": 0.25226024626477395,
      "price_change_percentage_24h": 3.78706,
      "price_change_percentage_7d": 10.874716867488363,
      "price_change_percentage_30d": -6.674544158759091
    },
    {
      "id": "gho",
      "symbol": "gho",
      "name": "GHO",
      "image": "https://coin-images.coingecko.com/coins/images/30663/large/gho-token-logo.png?1720517092",
      "current_price": 0.999383,
      "market_cap": 583654734,
      "market_cap_rank": 91,
      "price_change_percentage_1h": -0.007185838283884068,
      "price_change_percentage_24h": 0.0146,
      "price_change_percentage_7d": 0.03928792276659974,
      "price_change_percentage_30d": -0.06814191390588469
    },
    {
      "id": "arbitrum",
      "symbol": "arb",
      "name": "Arbitrum",
      "image": "https://coin-images.coingecko.com/coins/images/16547/large/arb.jpg?1721358242",
      "current_price": 0.09536,
      "market_cap": 576148973,
      "market_cap_rank": 92,
      "price_change_percentage_1h": -0.26187298847057766,
      "price_change_percentage_24h": 4.61372,
      "price_change_percentage_7d": 4.447843453557746,
      "price_change_percentage_30d": -4.637515132683658
    },
    {
      "id": "stable-2",
      "symbol": "stable",
      "name": "​​Stable",
      "image": "https://coin-images.coingecko.com/coins/images/69242/large/stable-logotype-framed-square-light.png?1762753913",
      "current_price": 0.02658656,
      "market_cap": 572673385,
      "market_cap_rank": 93,
      "price_change_percentage_1h": -0.16042606281339075,
      "price_change_percentage_24h": -5.59393,
      "price_change_percentage_7d": 6.623113959680456,
      "price_change_percentage_30d": -7.800589022070037
    },
    {
      "id": "just",
      "symbol": "jst",
      "name": "JUST",
      "image": "https://coin-images.coingecko.com/coins/images/11095/large/JUST.jpg?1696511035",
      "current_price": 0.063306,
      "market_cap": 557695332,
      "market_cap_rank": 94,
      "price_change_percentage_1h": -0.30279591007474793,
      "price_change_percentage_24h": 0.92658,
      "price_change_percentage_7d": 8.767744164198543,
      "price_change_percentage_30d": 29.599373209679996
    },
    {
      "id": "usual-usd",
      "symbol": "usd0",
      "name": "Usual USD",
      "image": "https://coin-images.coingecko.com/coins/images/38272/large/USD0LOGO.png?1716962811",
      "current_price": 0.997296,
      "market_cap": 557099435,
      "market_cap_rank": 95,
      "price_change_percentage_1h": -0.23201331616749293,
      "price_change_percentage_24h": -0.11986,
      "price_change_percentage_7d": -0.06332197770877267,
      "price_change_percentage_30d": -0.10256853547863044
    },
    {
      "id": "pancakeswap-token",
      "symbol": "cake",
      "name": "PancakeSwap",
      "image": "https://coin-images.coingecko.com/coins/images/12632/large/pancakeswap-cake-logo_%281%29.png?1696512440",
      "current_price": 1.44,
      "market_cap": 555152309,
      "market_cap_rank": 96,
      "price_change_percentage_1h": 0.38893412132914373,
      "price_change_percentage_24h": 2.5664,
      "price_change_percentage_7d": 3.4465889697498935,
      "price_change_percentage_30d": 7.263957425662297
    },
    {
      "id": "fetch-ai",
      "symbol": "fet",
      "name": "Artificial Superintelligence Alliance",
      "image": "https://coin-images.coingecko.com/coins/images/5681/large/ASI.png?1719827289",
      "current_price": 0.237262,
      "market_cap": 536633351,
      "market_cap_rank": 97,
      "price_change_percentage_1h": -0.8107461583391232,
      "price_change_percentage_24h": 3.58719,
      "price_change_percentage_7d": -2.1113897235121937,
      "price_change_percentage_30d": 63.01353841799282
    },
    {
      "id": "bonk",
      "symbol": "bonk",
      "name": "Bonk",
      "image": "https://coin-images.coingecko.com/coins/images/28600/large/bonk.jpg?1696527587",
      "current_price": 0.00000577,
      "market_cap": 507933364,
      "market_cap_rank": 98,
      "price_change_percentage_1h": -0.6572220347775302,
      "price_change_percentage_24h": 3.66197,
      "price_change_percentage_7d": -1.1868043654329448,
      "price_change_percentage_30d": -1.1528283307295049
    },
    {
      "id": "true-usd",
      "symbol": "tusd",
      "name": "TrueUSD",
      "image": "https://coin-images.coingecko.com/coins/images/3449/large/tusd.png?1696504140",
      "current_price": 0.999097,
      "market_cap": 493995940,
      "market_cap_rank": 99,
      "price_change_percentage_1h": 0.004148036473002947,
      "price_change_percentage_24h": -0.03938,
      "price_change_percentage_7d": 0.1864998402451722,
      "price_change_percentage_30d": -0.07547275201912679
    },
    {
      "id": "a7a5",
      "symbol": "a7a5",
      "name": "A7A5",
      "image": "https://coin-images.coingecko.com/coins/images/66657/large/A7A5_200.png?1750163839",
      "current_price": 0.0124006,
      "market_cap": 486104054,
      "market_cap_rank": 100,
      "price_change_percentage_1h": -0.0002872889099053999,
      "price_change_percentage_24h": -0.15176,
      "price_change_percentage_7d": 0.8236787511447959,
      "price_change_percentage_30d": -1.832526232565217
    }
  ],
  "count": 100,
  "timestamp": 1775455660268,
  "updatedAt": "2026-04-06T06:07:40.268Z"
}